README.rst
setup.py
tidalstream_dummy.egg-info/PKG-INFO
tidalstream_dummy.egg-info/SOURCES.txt
tidalstream_dummy.egg-info/dependency_links.txt
tidalstream_dummy.egg-info/top_level.txt
tsdummy/__init__.py
tsdummy/apps.py
tsdummy/handler.py
tsdummy/models.py
tsdummy/views.py
tsdummy/migrations/0001_initial.py
tsdummy/migrations/__init__.py