Metadata-Version: 1.1
Name: tidalstream-dummy
Version: 1.0.15
Summary: Dummy Tidalstream plugin
Home-page: https://github.com/tidalstream/plugin-service-dummy
Author: Anders Jensen
Author-email: johndoee@tidalstream.org
License: MIT
Keywords: tidalstream,plugin_type:service
Platform: UNKNOWN
Classifier: Development Status :: 3 - Alpha
Classifier: Environment :: Web Environment
Classifier: Intended Audience :: End Users/Desktop
Classifier: License :: OSI Approved :: MIT License
Classifier: Operating System :: OS Independent
Classifier: Programming Language :: Python
Classifier: Programming Language :: Python :: 2
Classifier: Programming Language :: Python :: 2.7
Classifier: Topic :: Internet :: WWW/HTTP
